webdriver_auto_update/__init__.py
webdriver_auto_update/chrome_app_utils.py
webdriver_auto_update/main.py
webdriver_auto_update/webdriver_manager.py
webdriver_auto_update-1.2.1.dist-info/LICENSE.txt
webdriver_auto_update-1.2.1.dist-info/METADATA
webdriver_auto_update-1.2.1.dist-info/WHEEL
webdriver_auto_update-1.2.1.dist-info/top_level.txt
webdriver_auto_update-1.2.1.dist-info/RECORD
