Metadata-Version: 2.1
Name: webdriver-auto-update
Version: 1.2.1
Summary: A tool for managing ChromeDriver downloads and updates
Home-page: https://github.com/competencytestlvl/webdriver_auto_update
Author: Rony Khong
Author-email: ronykhong77@gmail.com
Keywords: auto,browser,chrome,driver,download,selenium,update,web,webdriver
Classifier: Programming Language :: Python :: 3
Classifier: License :: OSI Approved :: MIT License
Classifier: Operating System :: OS Independent
Requires-Python: >=3.9
License-File: LICENSE.txt
Requires-Dist: requests
Requires-Dist: wget
